{
  "version": 3,
  "middleware": {
    "/": {
      "files": [
        "server/edge/chunks/Desktop_Jo's stash_aj247-site_website_edge-wrapper_49403e64.js",
        "server/edge/chunks/[root-of-the-server]__c16794f5._.js",
        "server/edge/chunks/turbopack-Desktop_Jo's stash_aj247-site_website_edge-wrapper_d76ad277.js"
      ],
      "name": "middleware",
      "page": "/",
      "matchers": [
        {
          "regexp": "^(?:\\/(_next\\/data\\/[^/]{1,}))?\\/client(?:\\/((?:[^\\/#\\?]+?)(?:\\/(?:[^\\/#\\?]+?))*))?(\\\\.json)?[\\/#\\?]?$",
          "originalSource": "/client/:path*"
        },
        {
          "regexp": "^(?:\\/(_next\\/data\\/[^/]{1,}))?\\/admin(?:\\/((?:[^\\/#\\?]+?)(?:\\/(?:[^\\/#\\?]+?))*))?(\\\\.json)?[\\/#\\?]?$",
          "originalSource": "/admin/:path*"
        }
      ],
      "wasm": [],
      "assets": [],
      "env": {
        "__NEXT_BUILD_ID": "Ir-1d3CDjqJSf5koVgR4S",
        "NEXT_SERVER_ACTIONS_ENCRYPTION_KEY": "WDHMuBphgpdKPhPG8HM4Zj3gEnse8cFngPTKB+GBxAQ=",
        "__NEXT_PREVIEW_MODE_ID": "88d79d462f57a125ce551a5ba5cb1e2e",
        "__NEXT_PREVIEW_MODE_ENCRYPTION_KEY": "84d825891333abb5aec6de52f14e714975d8b0724879da1f8758ae75df04c1a5",
        "__NEXT_PREVIEW_MODE_SIGNING_KEY": "2382d74171042eb95a900b94d82502b03573a4efaaa7d2d812b2eb44f2a0894f"
      }
    }
  },
  "sortedMiddleware": [
    "/"
  ],
  "functions": {}
}